Workbook

Sheet Customer_Details
A1: Customer Field | B1: Value
A2: Customer Name | B2: M/s. AMBAY ENGINEERING CORPORATION
A3: To | B3: Mr. Abhishek Singh
A4: Mobile
A5: Email
A6: GSTIN
A7: Address | B7: Plot No. 2, Sasouli Road, Yamuna Nagar - 135001 (Hr.)
A8: City / State
A9: Reference / Enquiry No.
A10: Customer Code

Sheet Quotation_Details
A1: Quotation Field | B1: Value
A2: Quotation No. | B2: SMS26025.1
A3: Date | B3: 08-Jun-2026
A4: Validity | B4: 15 Days
A5: Proposal Title | B5: TECHNO-COMMERCIAL PROPOSAL
A6: Product Title | B6: Supply of Parker 590P 4Q DC Drive 270A
A7: Product Subtitle | B7: with Feedback Card & Commissioning Support
A8: Prepared By | B8: SMS Controls & Automation
A9: Document Type | B9: Techno Commercial Proposal

Sheet Static_Content
A1: Static Field | B1: Value
A2: Salutation | B2: Dear Sir,
A3: Intro Text | B3: Thank you for giving SMS Controls & Automation the opportunity to submit this techno-commercial proposal. Based on your requirements and our discussion, we are pleased to offer a reliable DC drive solution with engineering and commissioning support.
A4: Company Overview | B4: SMS Controls & Automation provides industrial automation solutions including engineering, control panels, drive modernization, software development, commissioning, technical support and repair services for industrial electronics.
A5: Industry Text | B5: Our team brings strong field experience across metal, cable, packaging, paper, printing, textile, plastic, and process industries.
A6: Price Notes | B6: Taxes are extra as per actual. Freight extra on an actual basis.
A7: Thank You Text | B7: We appreciate the opportunity to present our proposal and look forward to becoming your trusted partner for industrial automation solutions.
A8: Experience Metric | B8: 15+
A9: Experience Label | B9: Years Experience
A10: Drive Metric | B10: AC/DC
A11: Drive Label | B11: Drive Specialist
A12: Tech Metric | B12: PLC/HMI
... A22: Footer | B22: SMS Controls & Automation | info@smscontrols.com | +91-8826059159 / 8595231536

Sheet Items
A1: Sr. No. | B1: Description | C1: Qty | D1: Unit | E1: Unit Price | F1: Discount % | G1: Gross Amount | H1: Discount Amount | I1: Discounted Price | J1: GST % | K1: GST Amount | M1: Summary | N1: Calculated Value
A2: 1 | B2: Parker 590P 4Q DC Drive 270A | C2: 1 | D2: No | E2: 277000 | F2: 0.06 | G2: =IF(B2="","",C2*E2) | H2: =IF(B2="","",G2*F2) | I2: =IF(B2="","",G2-H2) | J2: =IF(B2="","",Settings!$B$11) | K2: =IF(B2="","",I2*J2) | M2: Original Offer Value | N2: =SUM(G2:G11)
A3: 2 | B3: Tachometer Feedback Card | C3: 1 | D3: No | E3: 18500 | F3: 0.06 | G3: =IF(B3="","",C3*E3) | H3: =IF(B3="","",G3*F3) | I3: =IF(B3="","",G3-H3) | J3: =IF(B3="","",Settings!$B$11) | K3: =IF(B3="","",I3*J3) | M3: Total Discount | N3: =SUM(H2:H11)
A4: 3 | B4: Commissioning / Programming Support | C4: 1 | D4: Day | E4: 12500 | F4: 0.06 | G4: =IF(B4="","",C4*E4) | H4: =IF(B4="","",G4*F4) | I4: =IF(B4="","",G4-H4) | J4: =IF(B4="","",Settings!$B$11) | K4: =IF(B4="","",I4*J4) | M4: Final Offer Value | N4: =SUM(I2:I11)
A5: 4 | G5: =IF(B5="","",C5*E5) | H5: =IF(B5="","",G5*F5) | I5: =IF(B5="","",G5-H5) | J5: =IF(B5="","",Settings!$B$11) | K5: =IF(B5="","",I5*J5) | M5: GST % | N5: =Settings!B11
A6: 5 | G6: =IF(B6="","",C6*E6) | H6: =IF(B6="","",G6*F6) | I6: =IF(B6="","",G6-H6) | J6: =IF(B6="","",Settings!$B$11) | K6: =IF(B6="","",I6*J6) | M6: GST Amount | N6: =SUM(K2:K11)
A7: 6 | G7: =IF(B7="","",C7*E7) | H7: =IF(B7="","",G7*F7) | I7: =IF(B7="","",G7-H7) | J7: =IF(B7="","",Settings!$B$11) | K7: =IF(B7="","",I7*J7) | M7: Grand Total Incl. GST | N7: =N4+N6
A8: 7 | G8: =IF(B8="","",C8*E8) | H8: =IF(B8="","",G8*F8) | I8: =IF(B8="","",G8-H8) | J8: =IF(B8="","",Settings!$B$11) | K8: =IF(B8="","",I8*J8) | M8: Amount in Words | N8: Generated by Python script
A9: 8 | G9: =IF(B9="","",C9*E9) | H9: =IF(B9="","",G9*F9) | I9: =IF(B9="","",G9-H9) | J9: =IF(B9="","",Settings!$B$11) | K9: =IF(B9="","",I9*J9)
A10: 9 | G10: =IF(B10="","",C10*E10) | H10: =IF(B10="","",G10*F10) | I10: =IF(B10="","",G10-H10) | J10: =IF(B10="","",Settings!$B$11) | K10: =IF(B10="","",I10*J10)
A11: 10 | G11: =IF(B11="","",C11*E11) | H11: =IF(B11="","",G11*F11) | I11: =IF(B11="","",G11-H11) | J11: =IF(B11="","",Settings!$B$11) | K11: =IF(B11="","",I11*J11)

Sheet Terms
A1: Parameter | B1: Details
A2: Payment Terms | B2: 100% Advance against Proforma Invoice
A3: Delivery | B3: 1 - 2 Weeks
A4: Warranty | B4: 12 Months from the date of billing
A5: Price Basis | B5: Ex-Works: SMS Controls & Automation, Ghaziabad
A6: GST | B6: Extra @18%
A7: Freight & Insurance | B7: Extra as actual
A8: Commissioning | B8: As mentioned in scope. Lodging & boarding to be borne by buyer, if applicable.
A9: Offer Validity | B9: 15 Days from the date of quote
A10: Customer Scope 1 | B10: Electrical cabling and termination
A11: Customer Scope 2 | B11: Mechanical modification, if any
A12: Customer Scope 3 | B12: Civil work related to panel/machine
... A14: Exceptional Conditions | B14: Any interruption due to circumstances beyond reasonable control such as strikes, lockouts, war-like conditions, epidemics or natural calamities shall be mutually discussed. Expenses for re-deputation, if required, shall be to customer account.

Sheet Settings
A1: Setting | B1: Value
A2: Company Name | B2: SMS Controls & Automation
A3: Tagline | B3: Industrial Automation, Drives & Services
A4: Email | B4: info@smscontrols.com
A5: Mobile | B5: +91-8826059159 / 8595231536
A6: Address | B6: Office No. 2, Plot No. 241, Loha Mandi, Ghaziabad, Uttar Pradesh
A7: Bank Name | B7: Punjab National Bank
A8: Account No. | B8: 9698002100000689
A9: IFSC | B9: PUNB0969800
A10: GSTIN | B10: 09JSMPS2386Q1ZB
A11: Default GST % | B11: 0.18
A12: Logo Path | B12: assets/logo_from_doc.png
A13: Industry Image Path | B13: assets/industry_collage.png
A14: Output Folder | B14: output
A15: Currency Symbol | B15: ₹
